mailtrap_handler/MailTrapHandler.py
mailtrap_handler/__init__.py
mailtrap_handler-0.2.0.dist-info/LICENSE
mailtrap_handler-0.2.0.dist-info/METADATA
mailtrap_handler-0.2.0.dist-info/WHEEL
mailtrap_handler-0.2.0.dist-info/top_level.txt
mailtrap_handler-0.2.0.dist-info/RECORD
