Metadata-Version: 2.1
Name: mailtrap-handler
Version: 0.2.0
Home-page: https://github.com/trustedshops-public/python-mailtrap-handler
Author: Said Tahali (trusta)
Requires-Python: >3.8.0
License-File: LICENSE
Requires-Dist: polling (==0.3.2)
Requires-Dist: requests (==2.28.2)
